selenium_driver_updater/__init__.py
selenium_driver_updater/_chromeDriver.py
selenium_driver_updater/_edgeDriver.py
selenium_driver_updater/_geckoDriver.py
selenium_driver_updater/_operaDriver.py
selenium_driver_updater/_safari_driver.py
selenium_driver_updater/_setting.py
selenium_driver_updater/consoleUpdater.py
selenium_driver_updater/driverUpdater.py
selenium_driver_updater/driver_base.py
selenium_driver_updater/browsers/__init__.py
selenium_driver_updater/browsers/_chromeBrowser.py
selenium_driver_updater/browsers/_edgeBrowser.py
selenium_driver_updater/browsers/_firefoxBrowser.py
selenium_driver_updater/browsers/_operaBrowser.py
selenium_driver_updater/util/__init__.py
selenium_driver_updater/util/exceptions.py
selenium_driver_updater/util/extractor.py
selenium_driver_updater/util/github_viewer.py
selenium_driver_updater/util/logger.py
selenium_driver_updater/util/requests_getter.py
selenium_driver_updater-7.0.1.dist-info/LICENSE
selenium_driver_updater-7.0.1.dist-info/METADATA
selenium_driver_updater-7.0.1.dist-info/WHEEL
selenium_driver_updater-7.0.1.dist-info/entry_points.txt
selenium_driver_updater-7.0.1.dist-info/top_level.txt
selenium_driver_updater-7.0.1.dist-info/RECORD
