Metadata-Version: 2.2
Name: selenium_driver_updater
Version: 7.0.1
Summary: Download or update your Selenium driver binaries and their browsers automatically with this package
Home-page: https://github.com/stasvinokur/selenium_driver_updater
Author: Stanislav Vinokur
Author-email: stasvinokur@yahoo.com
License: MIT
Keywords: chromedriver,operadriver,edgedriver,safaridriver,selenium,seleniumdriver,chromedriver-binary,selenium-binary,selenium-python,selenium-driver,geckodriver,geckodriver-binary,operadriver-binary,edgedriver-binary,safaridriver-binary,chromebrowser,chrome-browser,firefox,firefox-browser,selenium-update,selenium-updater,updater
Classifier: Development Status :: 5 - Production/Stable
Classifier: Operating System :: Microsoft :: Windows :: Windows 10
Classifier: License :: OSI Approved :: MIT License
Classifier: Programming Language :: Python :: 3
Classifier: Programming Language :: Python
Classifier: Topic :: Software Development :: Libraries
Classifier: Topic :: Utilities
Classifier: Operating System :: MacOS
Classifier: Operating System :: Microsoft :: Windows
Classifier: Operating System :: POSIX :: Linux
License-File: LICENSE
Requires-Dist: wget
Requires-Dist: requests
Requires-Dist: selenium
Requires-Dist: beautifulsoup4
Requires-Dist: packaging
Dynamic: author
Dynamic: author-email
Dynamic: classifier
Dynamic: description
Dynamic: description-content-type
Dynamic: home-page
Dynamic: keywords
Dynamic: license
Dynamic: requires-dist
Dynamic: summary
